hooksff/__init__.py
hooksff/py.typed
hooksff-0.1.0.dist-info/LICENSE
hooksff-0.1.0.dist-info/METADATA
hooksff-0.1.0.dist-info/WHEEL
hooksff-0.1.0.dist-info/top_level.txt
hooksff-0.1.0.dist-info/RECORD
