Metadata-Version: 2.1
Name: hooksff
Version: 0.1.0
Summary: Hooks for functions.
Home-page: https://github.com/koviubi56/hooksff
Author: Koviubi56
Author-email: koviubi56@duck.com
License: MIT
Keywords: hooksff,hook,hooks
Platform: unix
Platform: linux
Platform: osx
Platform: cygwin
Platform: win32
Classifier: Development Status :: 3 - Alpha
Classifier: License :: OSI Approved :: MIT License
Classifier: Programming Language :: Python :: 3
Classifier: Programming Language :: Python :: 3 :: Only
Classifier: Programming Language :: Python :: 3.7
Classifier: Programming Language :: Python :: 3.8
Classifier: Programming Language :: Python :: 3.9
Classifier: Programming Language :: Python :: 3.10
Requires-Python: >=3.7
License-File: LICENSE
Requires-Dist: typing-extensions (>=3.10.0.0)
